pybgen/__init__.py
pybgen/parallel.py
pybgen/pybgen.py
pybgen/version.py
pybgen/tests/__init__.py
pybgen/tests/__main__.py
pybgen/tests/test_parallel.py
pybgen/tests/test_pybgen.py
pybgen/tests/truths.py
pybgen/tests/data/README.mkd
pybgen/tests/data/cohort1.bgen
pybgen/tests/data/cohort1.bgen.bgi
pybgen/tests/data/cohort1.probs.truths.txt.bz2
pybgen/tests/data/cohort1.truths.txt.bz2
pybgen/tests/data/example.16bits.bgen
pybgen/tests/data/example.16bits.bgen.bgi
pybgen/tests/data/example.16bits.probs.truths.txt.bz2
pybgen/tests/data/example.16bits.truths.txt.bz2
pybgen/tests/data/example.16bits.zstd.bgen
pybgen/tests/data/example.16bits.zstd.bgen.bgi
pybgen/tests/data/example.16bits.zstd.probs.truths.txt.bz2
pybgen/tests/data/example.16bits.zstd.truths.txt.bz2
pybgen/tests/data/example.24bits.bgen
pybgen/tests/data/example.24bits.bgen.bgi
pybgen/tests/data/example.24bits.probs.truths.txt.bz2
pybgen/tests/data/example.24bits.truths.txt.bz2
pybgen/tests/data/example.32bits.bgen
pybgen/tests/data/example.32bits.bgen.bgi
pybgen/tests/data/example.32bits.probs.truths.txt.bz2
pybgen/tests/data/example.32bits.truths.txt.bz2
pybgen/tests/data/example.3bits.bgen
pybgen/tests/data/example.3bits.bgen.bgi
pybgen/tests/data/example.3bits.probs.truths.txt.bz2
pybgen/tests/data/example.3bits.truths.txt.bz2
pybgen/tests/data/example.8bits.bgen
pybgen/tests/data/example.8bits.bgen.bgi
pybgen/tests/data/example.8bits.probs.truths.txt.bz2
pybgen/tests/data/example.8bits.truths.txt.bz2
pybgen/tests/data/example.9bits.bgen
pybgen/tests/data/example.9bits.bgen.bgi
pybgen/tests/data/example.9bits.probs.truths.txt.bz2
pybgen/tests/data/example.9bits.truths.txt.bz2
pybgen-0.7.1.dist-info/LICENSE.txt
pybgen-0.7.1.dist-info/METADATA
pybgen-0.7.1.dist-info/WHEEL
pybgen-0.7.1.dist-info/top_level.txt
pybgen-0.7.1.dist-info/RECORD
