Metadata-Version: 2.1
Name: pybgen
Version: 0.7.1
Summary: Python module to read BGEN files.
Home-page: https://github.com/lemieuxl/pybgen
Author: Louis-Philippe Lemieux Perreault
Author-email: louis-philippe.lemieux.perreault@statgen.org
License: MIT
Keywords: bioinformatics format BGEN binary
Platform: UNKNOWN
Classifier: Operating System :: POSIX :: Linux
Classifier: Operating System :: MacOS :: MacOS X
Classifier: Operating System :: Microsoft
Classifier: Programming Language :: Python
Classifier: Programming Language :: Python :: 2.7
Classifier: Programming Language :: Python :: 3
Classifier: Programming Language :: Python :: 3.6
Classifier: Programming Language :: Python :: 3.7
Classifier: Programming Language :: Python :: 3.8
Classifier: License :: OSI Approved :: MIT License
Classifier: Topic :: Scientific/Engineering :: Bio-Informatics
Requires-Dist: numpy (>=1.12.0)
Requires-Dist: six (>=1.10.0)
Requires-Dist: setuptools (>=27.0)
